CHANGES.rst
CONTRIBUTORS.rst
MANIFEST.in
Makefile
README.rst
base.cfg
buildout.cfg
dev.cfg
setup.py
sources.cfg
versions.cfg
.tx/config
docs/LICENSE.GPL
docs/LICENSE.rst
src/imio/__init__.py
src/imio.actionspanel.egg-info/PKG-INFO
src/imio.actionspanel.egg-info/SOURCES.txt
src/imio.actionspanel.egg-info/dependency_links.txt
src/imio.actionspanel.egg-info/entry_points.txt
src/imio.actionspanel.egg-info/namespace_packages.txt
src/imio.actionspanel.egg-info/not-zip-safe
src/imio.actionspanel.egg-info/requires.txt
src/imio.actionspanel.egg-info/top_level.txt
src/imio/actionspanel/__init__.py
src/imio/actionspanel/adapters.py
src/imio/actionspanel/config.py
src/imio/actionspanel/configure.zcml
src/imio/actionspanel/events.py
src/imio/actionspanel/interfaces.py
src/imio/actionspanel/mk_sync_locales.sh
src/imio/actionspanel/testing.py
src/imio/actionspanel/testing.zcml
src/imio/actionspanel/upgrades.zcml
src/imio/actionspanel/utils.py
src/imio/actionspanel/browser/__init__.py
src/imio/actionspanel/browser/actions_panel.pt
src/imio/actionspanel/browser/actions_panel_actions.pt
src/imio/actionspanel/browser/actions_panel_add_content.pt
src/imio/actionspanel/browser/actions_panel_arrows.pt
src/imio/actionspanel/browser/actions_panel_edit.pt
src/imio/actionspanel/browser/actions_panel_ext_edit.pt
src/imio/actionspanel/browser/actions_panel_folder_contents.pt
src/imio/actionspanel/browser/actions_panel_history.pt
src/imio/actionspanel/browser/actions_panel_own_delete.pt
src/imio/actionspanel/browser/actions_panel_own_delete_with_comments.pt
src/imio/actionspanel/browser/actions_panel_transitions.pt
src/imio/actionspanel/browser/actions_panel_viewlet.pt
src/imio/actionspanel/browser/comment_delete.pt
src/imio/actionspanel/browser/comment_transition.pt
src/imio/actionspanel/browser/comments.py
src/imio/actionspanel/browser/configure.zcml
src/imio/actionspanel/browser/jsvariables.py
src/imio/actionspanel/browser/registry.py
src/imio/actionspanel/browser/viewlets.py
src/imio/actionspanel/browser/views.py
src/imio/actionspanel/browser/static/actionspanel.css
src/imio/actionspanel/browser/static/actionspanel.js
src/imio/actionspanel/browser/static/arrowBottom.png
src/imio/actionspanel/browser/static/arrowDown.png
src/imio/actionspanel/browser/static/arrowTop.png
src/imio/actionspanel/browser/static/arrowUp.png
