Metadata-Version: 2.1
Name: imio.actionspanel
Version: 1.70
Summary: Actions panel
Home-page: https://github.com/imio/imio.actionspanel
Author: IMIO
Author-email: dev@imio.be
License: GPL
Download-URL: https://pypi.org/project/imio.actionspanel
Keywords: actions panel buttons
Platform: UNKNOWN
Classifier: Development Status :: 5 - Production/Stable
Classifier: Environment :: Web Environment
Classifier: Framework :: Plone
Classifier: Framework :: Plone :: 4.3
Classifier: License :: OSI Approved :: GNU General Public License v2 (GPLv2)
Classifier: Operating System :: OS Independent
Classifier: Programming Language :: Python
Classifier: Programming Language :: Python :: 2
Classifier: Programming Language :: Python :: 2.7
Provides-Extra: test
